galaxy/comm/__init__.py
galaxy/comm/constant.py
galaxy/comm/graphql/__init__.py
galaxy/comm/graphql/graphql.py
galaxy/comm/mail/__init__.py
galaxy/comm/mail/generator.py
galaxy/comm/mail/mail.py
galaxy_py_comm-0.0.6.dist-info/AUTHORS
galaxy_py_comm-0.0.6.dist-info/COPYING.md
galaxy_py_comm-0.0.6.dist-info/LICENSE.txt
galaxy_py_comm-0.0.6.dist-info/METADATA
galaxy_py_comm-0.0.6.dist-info/WHEEL
galaxy_py_comm-0.0.6.dist-info/RECORD
