Metadata-Version: 2.3
Name: galaxy-py-comm
Version: 0.0.6
Summary: Python Communication for the Galaxy Project
License: Apache-2.0
Keywords: galaxy,galaxy-comm
Author: Bastien Saltel
Author-email: bastien.saltel@gmail.com
Maintainer: Bastien Saltel
Maintainer-email: bastien.saltel@gmail.com
Requires-Python: >=3.10,<4.0
Classifier: Development Status :: 3 - Alpha
Classifier: Programming Language :: Python :: 3
Classifier: Operating System :: OS Independent
Requires-Dist: azure-identity
Requires-Dist: certifi
Requires-Dist: galaxy-py-net
Requires-Dist: galaxy-py-perfo
Requires-Dist: galaxy-py-service
Requires-Dist: galaxy-py-utils
Requires-Dist: msgraph-sdk
Requires-Dist: tenacity
Project-URL: Changelog, https://github.com/bsaltel/galaxy-py-comm/blob/main/CHANGELOG.md
Project-URL: Documentation, https://github.com/bsaltel/galaxy-py-comm
Project-URL: Homepage, https://github.com/bsaltel/galaxy-py-comm
Project-URL: Issues, https://github.com/bsaltel/galaxy-py-comm/issues
Project-URL: Repository, https://github.com/bsaltel/galaxy-py-comm.git
